{
    "data": [
        {
            "id": "4394557",
            "type": "article",
            "attributes": {
                "publishOn": "2020-12-14T08:50:29-05:00",
                "isLockedPro": false,
                "commentCount": 17,
                "gettyImageUrl": null,
                "videoPreviewUrl": null,
                "videoDuration": null,
                "themes": {},
                "title": "Huntington Ingalls Industries: Future Military Ship Mix May Be Different",
                "structuredInsights": null,
                "isPaywalled": false
            },
            "relationships": {
                "author": {
                    "data": {
                        "id": "103941",
                        "type": "author"
                    }
                },
                "sentiments": {
                    "data": [
                        {
                            "id": "304553",
                            "type": "sentiment"
                        }
                    ]
                },
                "primaryTickers": {
                    "data": [
                        {
                            "id": "18167",
                            "type": "tag"
                        }
                    ]
                },
                "secondaryTickers": {
                    "data": []
                },
                "otherTags": {
                    "data": []
                }
            },
            "links": {
                "self": "/article/4394557-huntington-ingalls-industries-future-military-ship-mix-may-be-different"
            }
        },
        {
            "id": "4379891",
            "type": "article",
            "attributes": {
                "publishOn": "2020-10-20T03:12:27-04:00",
                "isLockedPro": false,
                "commentCount": 23,
                "gettyImageUrl": null,
                "videoPreviewUrl": null,
                "videoDuration": null,
                "themes": {},
                "title": "Huntington Ingalls: Set For Massive Outperformance In The Coming Years",
                "structuredInsights": null,
                "isPaywalled": false
            },
            "relationships": {
                "author": {
                    "data": {
                        "id": "103239",
                        "type": "author"
                    }
                },
                "sentiments": {
                    "data": [
                        {
                            "id": "296987",
                            "type": "sentiment"
                        }
                    ]
                },
                "primaryTickers": {
                    "data": [
                        {
                            "id": "18167",
                            "type": "tag"
                        }
                    ]
                },
                "secondaryTickers": {
                    "data": []
                },
                "otherTags": {
                    "data": []
                }
            },
            "links": {
                "self": "/article/4379891-huntington-ingalls-set-for-massive-outperformance-in-coming-years"
            }
        },
        {
            "id": "4376293",
            "type": "article",
            "attributes": {
                "publishOn": "2020-09-29T09:00:00-04:00",
                "isLockedPro": false,
                "commentCount": 11,
                "gettyImageUrl": null,
                "videoPreviewUrl": null,
                "videoDuration": null,
                "themes": {},
                "title": "COVID-19 + Election Uncertainty = Opportunity In Huntington Ingalls Industries, Inc. - Behind The Idea",
                "structuredInsights": null,
                "isPaywalled": false
            },
            "relationships": {
                "author": {
                    "data": {
                        "id": "103910",
                        "type": "author"
                    }
                },
                "sentiments": {
                    "data": [
                        {
                            "id": "293909",
                            "type": "sentiment"
                        }
                    ]
                },
                "primaryTickers": {
                    "data": [
                        {
                            "id": "18167",
                            "type": "tag"
                        }
                    ]
                },
                "secondaryTickers": {
                    "data": []
                },
                "otherTags": {
                    "data": []
                }
            },
            "links": {
                "self": "/article/4376293-covidminus-19-election-uncertainty-opportunity-in-huntington-ingalls-industries-inc-behind"
            }
        },
        {
            "id": "4375511",
            "type": "article",
            "attributes": {
                "publishOn": "2020-09-29T08:00:00-04:00",
                "isLockedPro": false,
                "commentCount": 18,
                "gettyImageUrl": null,
                "videoPreviewUrl": null,
                "videoDuration": null,
                "themes": {},
                "title": "COVID-19 + Election Uncertainty = Opportunity In Huntington Ingalls Industries, Inc.",
                "structuredInsights": null,
                "isPaywalled": false
            },
            "relationships": {
                "author": {
                    "data": {
                        "id": "95996",
                        "type": "author"
                    }
                },
                "sentiments": {
                    "data": [
                        {
                            "id": "292729",
                            "type": "sentiment"
                        }
                    ]
                },
                "primaryTickers": {
                    "data": [
                        {
                            "id": "18167",
                            "type": "tag"
                        }
                    ]
                },
                "secondaryTickers": {
                    "data": []
                },
                "otherTags": {
                    "data": [
                        {
                            "id": "49641",
                            "type": "tag"
                        }
                    ]
                }
            },
            "links": {
                "self": "/article/4375511-covidminus-19-election-uncertainty-opportunity-in-huntington-ingalls-industries-inc"
            }
        },
        {
            "id": "4375777",
            "type": "article",
            "attributes": {
                "publishOn": "2020-09-22T15:17:48-04:00",
                "isLockedPro": false,
                "commentCount": 9,
                "gettyImageUrl": null,
                "videoPreviewUrl": null,
                "videoDuration": null,
                "themes": {},
                "title": "Huntington Ingalls: Far From A Sinking Ship",
                "structuredInsights": null,
                "isPaywalled": false
            },
            "relationships": {
                "author": {
                    "data": {
                        "id": "105497",
                        "type": "author"
                    }
                },
                "sentiments": {
                    "data": [
                        {
                            "id": "293362",
                            "type": "sentiment"
                        }
                    ]
                },
                "primaryTickers": {
                    "data": [
                        {
                            "id": "18167",
                            "type": "tag"
                        }
                    ]
                },
                "secondaryTickers": {
                    "data": []
                },
                "otherTags": {
                    "data": []
                }
            },
            "links": {
                "self": "/article/4375777-huntington-ingalls-far-from-sinking-ship"
            }
        },
        {
            "id": "4372167",
            "type": "article",
            "attributes": {
                "publishOn": "2020-09-02T15:46:17-04:00",
                "isLockedPro": false,
                "commentCount": 82,
                "gettyImageUrl": null,
                "videoPreviewUrl": null,
                "videoDuration": null,
                "themes": {},
                "title": "Huntington Ingalls Is In Free-Fall, Yet You Should Still Buy It Now",
                "structuredInsights": null,
                "isPaywalled": false
            },
            "relationships": {
                "author": {
                    "data": {
                        "id": "103213",
                        "type": "author"
                    }
                },
                "sentiments": {
                    "data": [
                        {
                            "id": "290810",
                            "type": "sentiment"
                        }
                    ]
                },
                "primaryTickers": {
                    "data": [
                        {
                            "id": "18167",
                            "type": "tag"
                        }
                    ]
                },
                "secondaryTickers": {
                    "data": []
                },
                "otherTags": {
                    "data": []
                }
            },
            "links": {
                "self": "/article/4372167-huntington-ingalls-is-in-free-fall-yet-you-should-still-buy-now"
            }
        },
        {
            "id": "4369086",
            "type": "article",
            "attributes": {
                "publishOn": "2020-08-17T00:32:19-04:00",
                "isLockedPro": false,
                "commentCount": 80,
                "gettyImageUrl": null,
                "videoPreviewUrl": null,
                "videoDuration": null,
                "themes": {},
                "title": "Huntington Ingalls: Too Much Optimism For This Company",
                "structuredInsights": null,
                "isPaywalled": false
            },
            "relationships": {
                "author": {
                    "data": {
                        "id": "20449",
                        "type": "author"
                    }
                },
                "sentiments": {
                    "data": [
                        {
                            "id": "288235",
                            "type": "sentiment"
                        }
                    ]
                },
                "primaryTickers": {
                    "data": [
                        {
                            "id": "18167",
                            "type": "tag"
                        }
                    ]
                },
                "secondaryTickers": {
                    "data": []
                },
                "otherTags": {
                    "data": []
                }
            },
            "links": {
                "self": "/article/4369086-huntington-ingalls-too-much-optimism-for-this-company"
            }
        },
        {
            "id": "4368357",
            "type": "article",
            "attributes": {
                "publishOn": "2020-08-13T12:08:56-04:00",
                "isLockedPro": false,
                "commentCount": 18,
                "gettyImageUrl": null,
                "videoPreviewUrl": null,
                "videoDuration": null,
                "themes": {},
                "title": "Huntington Ingalls Industries: An Attractively Priced Shareholder Value-Creation Machine",
                "structuredInsights": null,
                "isPaywalled": false
            },
            "relationships": {
                "author": {
                    "data": {
                        "id": "105308",
                        "type": "author"
                    }
                },
                "sentiments": {
                    "data": [
                        {
                            "id": "288074",
                            "type": "sentiment"
                        }
                    ]
                },
                "primaryTickers": {
                    "data": [
                        {
                            "id": "18167",
                            "type": "tag"
                        }
                    ]
                },
                "secondaryTickers": {
                    "data": []
                },
                "otherTags": {
                    "data": []
                }
            },
            "links": {
                "self": "/article/4368357-huntington-ingalls-industries-attractively-priced-shareholder-value-creation-machine"
            }
        },
        {
            "id": "4364129",
            "type": "article",
            "attributes": {
                "publishOn": "2020-08-04T09:56:43-04:00",
                "isLockedPro": false,
                "commentCount": 21,
                "gettyImageUrl": null,
                "videoPreviewUrl": null,
                "videoDuration": null,
                "themes": {},
                "title": "Huntington Ingalls: Undervalued Leader In Naval Warfare",
                "structuredInsights": null,
                "isPaywalled": false
            },
            "relationships": {
                "author": {
                    "data": {
                        "id": "105634",
                        "type": "author"
                    }
                },
                "sentiments": {
                    "data": [
                        {
                            "id": "286653",
                            "type": "sentiment"
                        }
                    ]
                },
                "primaryTickers": {
                    "data": [
                        {
                            "id": "18167",
                            "type": "tag"
                        }
                    ]
                },
                "secondaryTickers": {
                    "data": []
                },
                "otherTags": {
                    "data": []
                }
            },
            "links": {
                "self": "/article/4364129-huntington-ingalls-undervalued-leader-in-naval-warfare"
            }
        },
        {
            "id": "4358125",
            "type": "article",
            "attributes": {
                "publishOn": "2020-07-13T10:17:52-04:00",
                "isLockedPro": false,
                "commentCount": 4,
                "gettyImageUrl": null,
                "videoPreviewUrl": null,
                "videoDuration": null,
                "themes": {},
                "title": "An Overview Of Huntington Ingalls Industries' Improving Free Cash Flow",
                "structuredInsights": null,
                "isPaywalled": false
            },
            "relationships": {
                "author": {
                    "data": {
                        "id": "99686",
                        "type": "author"
                    }
                },
                "sentiments": {
                    "data": [
                        {
                            "id": "283538",
                            "type": "sentiment"
                        }
                    ]
                },
                "primaryTickers": {
                    "data": [
                        {
                            "id": "18167",
                            "type": "tag"
                        }
                    ]
                },
                "secondaryTickers": {
                    "data": []
                },
                "otherTags": {
                    "data": []
                }
            },
            "links": {
                "self": "/article/4358125-overview-of-huntington-ingalls-industries-improving-free-cash-flow"
            }
        },
        {
            "id": "4357925",
            "type": "article",
            "attributes": {
                "publishOn": "2020-07-11T08:29:30-04:00",
                "isLockedPro": false,
                "commentCount": 24,
                "gettyImageUrl": null,
                "videoPreviewUrl": null,
                "videoDuration": null,
                "themes": {},
                "title": "Huntington Ingalls: A Value Stock That's Poised To Perform",
                "structuredInsights": null,
                "isPaywalled": false
            },
            "relationships": {
                "author": {
                    "data": {
                        "id": "105703",
                        "type": "author"
                    }
                },
                "sentiments": {
                    "data": [
                        {
                            "id": "283495",
                            "type": "sentiment"
                        }
                    ]
                },
                "primaryTickers": {
                    "data": [
                        {
                            "id": "18167",
                            "type": "tag"
                        }
                    ]
                },
                "secondaryTickers": {
                    "data": []
                },
                "otherTags": {
                    "data": []
                }
            },
            "links": {
                "self": "/article/4357925-huntington-ingalls-value-stock-poised-to-perform"
            }
        },
        {
            "id": "4356561",
            "type": "article",
            "attributes": {
                "publishOn": "2020-07-01T10:36:05-04:00",
                "isLockedPro": false,
                "commentCount": 9,
                "gettyImageUrl": null,
                "videoPreviewUrl": null,
                "videoDuration": null,
                "themes": {},
                "title": "Huntington Ingalls Industries: Build Wealth With This Shipbuilder",
                "structuredInsights": null,
                "isPaywalled": false
            },
            "relationships": {
                "author": {
                    "data": {
                        "id": "105395",
                        "type": "author"
                    }
                },
                "sentiments": {
                    "data": [
                        {
                            "id": "282101",
                            "type": "sentiment"
                        }
                    ]
                },
                "primaryTickers": {
                    "data": [
                        {
                            "id": "18167",
                            "type": "tag"
                        }
                    ]
                },
                "secondaryTickers": {
                    "data": []
                },
                "otherTags": {
                    "data": []
                }
            },
            "links": {
                "self": "/article/4356561-huntington-ingalls-industries-build-wealth-this-shipbuilder"
            }
        },
        {
            "id": "4349410",
            "type": "article",
            "attributes": {
                "publishOn": "2020-05-21T15:29:09-04:00",
                "isLockedPro": false,
                "commentCount": 18,
                "gettyImageUrl": null,
                "videoPreviewUrl": null,
                "videoDuration": null,
                "themes": {},
                "title": "A Once In A Decade Opportunity To Own Huntington Ingalls Industries",
                "structuredInsights": null,
                "isPaywalled": false
            },
            "relationships": {
                "author": {
                    "data": {
                        "id": "105709",
                        "type": "author"
                    }
                },
                "sentiments": {
                    "data": [
                        {
                            "id": "276162",
                            "type": "sentiment"
                        }
                    ]
                },
                "primaryTickers": {
                    "data": [
                        {
                            "id": "18167",
                            "type": "tag"
                        }
                    ]
                },
                "secondaryTickers": {
                    "data": []
                },
                "otherTags": {
                    "data": []
                }
            },
            "links": {
                "self": "/article/4349410-in-decade-opportunity-to-own-huntington-ingalls-industries"
            }
        },
        {
            "id": "4347707",
            "type": "article",
            "attributes": {
                "publishOn": "2020-05-14T16:36:01-04:00",
                "isLockedPro": false,
                "commentCount": 27,
                "gettyImageUrl": null,
                "videoPreviewUrl": null,
                "videoDuration": null,
                "themes": {},
                "title": "Huntington Ingalls: A Record Backlog And Undervaluation Mean Buy",
                "structuredInsights": null,
                "isPaywalled": false
            },
            "relationships": {
                "author": {
                    "data": {
                        "id": "20449",
                        "type": "author"
                    }
                },
                "sentiments": {
                    "data": [
                        {
                            "id": "275355",
                            "type": "sentiment"
                        }
                    ]
                },
                "primaryTickers": {
                    "data": [
                        {
                            "id": "18167",
                            "type": "tag"
                        }
                    ]
                },
                "secondaryTickers": {
                    "data": []
                },
                "otherTags": {
                    "data": []
                }
            },
            "links": {
                "self": "/article/4347707-huntington-ingalls-record-backlog-and-undervaluation-mean-buy"
            }
        },
        {
            "id": "4338008",
            "type": "article",
            "attributes": {
                "publishOn": "2020-04-16T13:28:27-04:00",
                "isLockedPro": false,
                "commentCount": 4,
                "gettyImageUrl": null,
                "videoPreviewUrl": null,
                "videoDuration": null,
                "themes": {},
                "title": "Huntington Ingalls Industries: A Large Backlog With Future Financial Value",
                "structuredInsights": null,
                "isPaywalled": false
            },
            "relationships": {
                "author": {
                    "data": {
                        "id": "103941",
                        "type": "author"
                    }
                },
                "sentiments": {
                    "data": [
                        {
                            "id": "270434",
                            "type": "sentiment"
                        }
                    ]
                },
                "primaryTickers": {
                    "data": [
                        {
                            "id": "18167",
                            "type": "tag"
                        }
                    ]
                },
                "secondaryTickers": {
                    "data": []
                },
                "otherTags": {
                    "data": []
                }
            },
            "links": {
                "self": "/article/4338008-huntington-ingalls-industries-large-backlog-future-financial-value"
            }
        },
        {
            "id": "4324019",
            "type": "article",
            "attributes": {
                "publishOn": "2020-02-13T15:14:21-05:00",
                "isLockedPro": false,
                "commentCount": 5,
                "gettyImageUrl": null,
                "videoPreviewUrl": null,
                "videoDuration": null,
                "themes": {},
                "title": "Huntington Ingalls Industries To Acquire Hydroid For UUV Tech",
                "structuredInsights": null,
                "isPaywalled": false
            },
            "relationships": {
                "author": {
                    "data": {
                        "id": "101421",
                        "type": "author"
                    }
                },
                "sentiments": {
                    "data": [
                        {
                            "id": "261265",
                            "type": "sentiment"
                        }
                    ]
                },
                "primaryTickers": {
                    "data": [
                        {
                            "id": "18167",
                            "type": "tag"
                        }
                    ]
                },
                "secondaryTickers": {
                    "data": []
                },
                "otherTags": {
                    "data": []
                }
            },
            "links": {
                "self": "/article/4324019-huntington-ingalls-industries-to-acquire-hydroid-for-uuv-tech"
            }
        },
        {
            "id": "4319685",
            "type": "article",
            "attributes": {
                "publishOn": "2020-01-29T00:00:57-05:00",
                "isLockedPro": false,
                "commentCount": 0,
                "gettyImageUrl": null,
                "videoPreviewUrl": null,
                "videoDuration": null,
                "themes": {},
                "title": "Dividend Growth Stocks Of Tomorrow: Huntington Ingalls Industries, Inc.",
                "structuredInsights": null,
                "isPaywalled": false
            },
            "relationships": {
                "author": {
                    "data": {
                        "id": "50452",
                        "type": "author"
                    }
                },
                "sentiments": {
                    "data": []
                },
                "primaryTickers": {
                    "data": [
                        {
                            "id": "18167",
                            "type": "tag"
                        }
                    ]
                },
                "secondaryTickers": {
                    "data": []
                },
                "otherTags": {
                    "data": []
                }
            },
            "links": {
                "self": "/article/4319685-dividend-growth-stocks-of-tomorrow-huntington-ingalls-industries-inc"
            }
        }
    ]
}