{
    "data": [
        {
            "id": "4313591",
            "type": "article",
            "attributes": {
                "publishOn": "2019-12-23T07:00:00-05:00",
                "isLockedPro": false,
                "commentCount": 119,
                "gettyImageUrl": null,
                "videoPreviewUrl": null,
                "videoDuration": null,
                "themes": {},
                "title": "Tech Is Just Getting Started Going Into 2020",
                "structuredInsights": null,
                "isPaywalled": false
            },
            "relationships": {
                "author": {
                    "data": {
                        "id": "102107",
                        "type": "author"
                    }
                },
                "sentiments": {
                    "data": []
                },
                "primaryTickers": {
                    "data": [
                        {
                            "id": "903",
                            "type": "tag"
                        }
                    ]
                },
                "secondaryTickers": {
                    "data": []
                },
                "otherTags": {
                    "data": [
                        {
                            "id": "1302",
                            "type": "tag"
                        }
                    ]
                }
            },
            "links": {
                "self": "/article/4313591-tech-is-just-getting-started-going-2020"
            }
        },
        {
            "id": "4312229",
            "type": "article",
            "attributes": {
                "publishOn": "2019-12-12T15:16:40-05:00",
                "isLockedPro": false,
                "commentCount": 16,
                "gettyImageUrl": null,
                "videoPreviewUrl": null,
                "videoDuration": null,
                "themes": {},
                "title": "Mastercard: A Story Of Healthy Volumes And Attractive Pricing",
                "structuredInsights": null,
                "isPaywalled": false
            },
            "relationships": {
                "author": {
                    "data": {
                        "id": "105417",
                        "type": "author"
                    }
                },
                "sentiments": {
                    "data": [
                        {
                            "id": "247105",
                            "type": "sentiment"
                        }
                    ]
                },
                "primaryTickers": {
                    "data": [
                        {
                            "id": "903",
                            "type": "tag"
                        }
                    ]
                },
                "secondaryTickers": {
                    "data": []
                },
                "otherTags": {
                    "data": []
                }
            },
            "links": {
                "self": "/article/4312229-mastercard-story-of-healthy-volumes-and-attractive-pricing"
            }
        },
        {
            "id": "4307627",
            "type": "article",
            "attributes": {
                "publishOn": "2019-11-19T00:20:49-05:00",
                "isLockedPro": false,
                "commentCount": 17,
                "gettyImageUrl": null,
                "videoPreviewUrl": null,
                "videoDuration": null,
                "themes": {},
                "title": "Now Mastercard Is A Buy",
                "structuredInsights": null,
                "isPaywalled": false
            },
            "relationships": {
                "author": {
                    "data": {
                        "id": "92456",
                        "type": "author"
                    }
                },
                "sentiments": {
                    "data": [
                        {
                            "id": "239530",
                            "type": "sentiment"
                        }
                    ]
                },
                "primaryTickers": {
                    "data": [
                        {
                            "id": "903",
                            "type": "tag"
                        }
                    ]
                },
                "secondaryTickers": {
                    "data": []
                },
                "otherTags": {
                    "data": []
                }
            },
            "links": {
                "self": "/article/4307627-now-mastercard-is-buy"
            }
        },
        {
            "id": "4305418",
            "type": "article",
            "attributes": {
                "publishOn": "2019-11-11T11:27:53-05:00",
                "isLockedPro": false,
                "commentCount": 11,
                "gettyImageUrl": null,
                "videoPreviewUrl": null,
                "videoDuration": null,
                "themes": {},
                "title": "Mastercard: Taking A Breather",
                "structuredInsights": null,
                "isPaywalled": false
            },
            "relationships": {
                "author": {
                    "data": {
                        "id": "33291",
                        "type": "author"
                    }
                },
                "sentiments": {
                    "data": [
                        {
                            "id": "80373",
                            "type": "sentiment"
                        }
                    ]
                },
                "primaryTickers": {
                    "data": [
                        {
                            "id": "903",
                            "type": "tag"
                        }
                    ]
                },
                "secondaryTickers": {
                    "data": []
                },
                "otherTags": {
                    "data": []
                }
            },
            "links": {
                "self": "/article/4305418-mastercard-taking-breather"
            }
        },
        {
            "id": "4302513",
            "type": "article",
            "attributes": {
                "publishOn": "2019-11-05T07:56:50-05:00",
                "isLockedPro": false,
                "commentCount": 70,
                "gettyImageUrl": null,
                "videoPreviewUrl": null,
                "videoDuration": null,
                "themes": {},
                "title": "Mastercard: Reiterate 15-18% Annual Return Buy Case After Q3",
                "structuredInsights": null,
                "isPaywalled": false
            },
            "relationships": {
                "author": {
                    "data": {
                        "id": "105096",
                        "type": "author"
                    }
                },
                "sentiments": {
                    "data": [
                        {
                            "id": "78709",
                            "type": "sentiment"
                        }
                    ]
                },
                "primaryTickers": {
                    "data": [
                        {
                            "id": "903",
                            "type": "tag"
                        }
                    ]
                },
                "secondaryTickers": {
                    "data": []
                },
                "otherTags": {
                    "data": []
                }
            },
            "links": {
                "self": "/article/4302513-mastercard-reiterate-15minus-18-percent-annual-return-buy-case-after-q3"
            }
        },
        {
            "id": "4302210",
            "type": "article",
            "attributes": {
                "publishOn": "2019-11-04T12:29:07-05:00",
                "isLockedPro": false,
                "commentCount": 15,
                "gettyImageUrl": null,
                "videoPreviewUrl": null,
                "videoDuration": null,
                "themes": {},
                "title": "Mastercard: 'Overvaluation' Masks Opportunity",
                "structuredInsights": null,
                "isPaywalled": false
            },
            "relationships": {
                "author": {
                    "data": {
                        "id": "41961",
                        "type": "author"
                    }
                },
                "sentiments": {
                    "data": [
                        {
                            "id": "78633",
                            "type": "sentiment"
                        }
                    ]
                },
                "primaryTickers": {
                    "data": [
                        {
                            "id": "903",
                            "type": "tag"
                        }
                    ]
                },
                "secondaryTickers": {
                    "data": []
                },
                "otherTags": {
                    "data": []
                }
            },
            "links": {
                "self": "/article/4302210-mastercard-overvaluation-masks-opportunity"
            }
        },
        {
            "id": "4302143",
            "type": "article",
            "attributes": {
                "publishOn": "2019-11-04T09:37:06-05:00",
                "isLockedPro": false,
                "commentCount": 18,
                "gettyImageUrl": null,
                "videoPreviewUrl": null,
                "videoDuration": null,
                "themes": {},
                "title": "Mastercard: Valuation Risk Continues To Rise",
                "structuredInsights": null,
                "isPaywalled": false
            },
            "relationships": {
                "author": {
                    "data": {
                        "id": "60561",
                        "type": "author"
                    }
                },
                "sentiments": {
                    "data": [
                        {
                            "id": "78722",
                            "type": "sentiment"
                        }
                    ]
                },
                "primaryTickers": {
                    "data": [
                        {
                            "id": "903",
                            "type": "tag"
                        }
                    ]
                },
                "secondaryTickers": {
                    "data": []
                },
                "otherTags": {
                    "data": []
                }
            },
            "links": {
                "self": "/article/4302143-mastercard-valuation-risk-continues-to-rise"
            }
        },
        {
            "id": "4298665",
            "type": "article",
            "attributes": {
                "publishOn": "2019-10-24T13:26:36-04:00",
                "isLockedPro": false,
                "commentCount": 34,
                "gettyImageUrl": null,
                "videoPreviewUrl": null,
                "videoDuration": null,
                "themes": {},
                "title": "Mastercard: Not A 'Strong Buy' At The Moment",
                "structuredInsights": null,
                "isPaywalled": false
            },
            "relationships": {
                "author": {
                    "data": {
                        "id": "92456",
                        "type": "author"
                    }
                },
                "sentiments": {
                    "data": [
                        {
                            "id": "76135",
                            "type": "sentiment"
                        }
                    ]
                },
                "primaryTickers": {
                    "data": [
                        {
                            "id": "903",
                            "type": "tag"
                        }
                    ]
                },
                "secondaryTickers": {
                    "data": []
                },
                "otherTags": {
                    "data": []
                }
            },
            "links": {
                "self": "/article/4298665-mastercard-not-strong-buy-moment"
            }
        },
        {
            "id": "4295762",
            "type": "article",
            "attributes": {
                "publishOn": "2019-10-09T13:29:22-04:00",
                "isLockedPro": false,
                "commentCount": 40,
                "gettyImageUrl": null,
                "videoPreviewUrl": null,
                "videoDuration": null,
                "themes": {},
                "title": "Mastercard: A 10-Year, Full-Cycle Analysis",
                "structuredInsights": null,
                "isPaywalled": false
            },
            "relationships": {
                "author": {
                    "data": {
                        "id": "95006",
                        "type": "author"
                    }
                },
                "sentiments": {
                    "data": [
                        {
                            "id": "72983",
                            "type": "sentiment"
                        }
                    ]
                },
                "primaryTickers": {
                    "data": [
                        {
                            "id": "903",
                            "type": "tag"
                        }
                    ]
                },
                "secondaryTickers": {
                    "data": []
                },
                "otherTags": {
                    "data": []
                }
            },
            "links": {
                "self": "/article/4295762-mastercard-10-year-full-cycle-analysis"
            }
        },
        {
            "id": "4294435",
            "type": "article",
            "attributes": {
                "publishOn": "2019-10-01T15:49:58-04:00",
                "isLockedPro": false,
                "commentCount": 9,
                "gettyImageUrl": null,
                "videoPreviewUrl": null,
                "videoDuration": null,
                "themes": {},
                "title": "Mastercard: Valuation Follow-Up",
                "structuredInsights": null,
                "isPaywalled": false
            },
            "relationships": {
                "author": {
                    "data": {
                        "id": "92456",
                        "type": "author"
                    }
                },
                "sentiments": {
                    "data": [
                        {
                            "id": "71540",
                            "type": "sentiment"
                        }
                    ]
                },
                "primaryTickers": {
                    "data": [
                        {
                            "id": "903",
                            "type": "tag"
                        }
                    ]
                },
                "secondaryTickers": {
                    "data": []
                },
                "otherTags": {
                    "data": []
                }
            },
            "links": {
                "self": "/article/4294435-mastercard-valuation-follow-up"
            }
        },
        {
            "id": "4294165",
            "type": "article",
            "attributes": {
                "publishOn": "2019-09-30T11:31:30-04:00",
                "isLockedPro": false,
                "commentCount": 66,
                "gettyImageUrl": null,
                "videoPreviewUrl": null,
                "videoDuration": null,
                "themes": {},
                "title": "Visa, Mastercard: Fintechs, A Boon, A Bust",
                "structuredInsights": null,
                "isPaywalled": false
            },
            "relationships": {
                "author": {
                    "data": {
                        "id": "25047",
                        "type": "author"
                    }
                },
                "sentiments": {
                    "data": [
                        {
                            "id": "70535",
                            "type": "sentiment"
                        },
                        {
                            "id": "70536",
                            "type": "sentiment"
                        }
                    ]
                },
                "primaryTickers": {
                    "data": [
                        {
                            "id": "903",
                            "type": "tag"
                        }
                    ]
                },
                "secondaryTickers": {
                    "data": []
                },
                "otherTags": {
                    "data": []
                }
            },
            "links": {
                "self": "/article/4294165-visa-mastercard-fintechs-boon-bust"
            }
        },
        {
            "id": "4293106",
            "type": "article",
            "attributes": {
                "publishOn": "2019-09-23T16:22:30-04:00",
                "isLockedPro": false,
                "commentCount": 13,
                "gettyImageUrl": null,
                "videoPreviewUrl": null,
                "videoDuration": null,
                "themes": {},
                "title": "Mastercard: Comparable Valuation",
                "structuredInsights": null,
                "isPaywalled": false
            },
            "relationships": {
                "author": {
                    "data": {
                        "id": "92456",
                        "type": "author"
                    }
                },
                "sentiments": {
                    "data": [
                        {
                            "id": "68952",
                            "type": "sentiment"
                        }
                    ]
                },
                "primaryTickers": {
                    "data": [
                        {
                            "id": "903",
                            "type": "tag"
                        }
                    ]
                },
                "secondaryTickers": {
                    "data": []
                },
                "otherTags": {
                    "data": []
                }
            },
            "links": {
                "self": "/article/4293106-mastercard-comparable-valuation"
            }
        },
        {
            "id": "4292992",
            "type": "article",
            "attributes": {
                "publishOn": "2019-09-23T09:55:27-04:00",
                "isLockedPro": false,
                "commentCount": 3,
                "gettyImageUrl": null,
                "videoPreviewUrl": null,
                "videoDuration": null,
                "themes": {},
                "title": "Mastercard's Fundamentals Sustain Its Price Momentum",
                "structuredInsights": null,
                "isPaywalled": false
            },
            "relationships": {
                "author": {
                    "data": {
                        "id": "102548",
                        "type": "author"
                    }
                },
                "sentiments": {
                    "data": [
                        {
                            "id": "65750",
                            "type": "sentiment"
                        }
                    ]
                },
                "primaryTickers": {
                    "data": [
                        {
                            "id": "903",
                            "type": "tag"
                        }
                    ]
                },
                "secondaryTickers": {
                    "data": []
                },
                "otherTags": {
                    "data": []
                }
            },
            "links": {
                "self": "/article/4292992-mastercards-fundamentals-sustain-price-momentum"
            }
        },
        {
            "id": "4292602",
            "type": "article",
            "attributes": {
                "publishOn": "2019-09-19T21:02:58-04:00",
                "isLockedPro": false,
                "commentCount": 10,
                "gettyImageUrl": null,
                "videoPreviewUrl": null,
                "videoDuration": null,
                "themes": {},
                "title": "Mastercard: Vast Opportunities Ahead",
                "structuredInsights": null,
                "isPaywalled": false
            },
            "relationships": {
                "author": {
                    "data": {
                        "id": "105354",
                        "type": "author"
                    }
                },
                "sentiments": {
                    "data": [
                        {
                            "id": "68675",
                            "type": "sentiment"
                        }
                    ]
                },
                "primaryTickers": {
                    "data": [
                        {
                            "id": "903",
                            "type": "tag"
                        }
                    ]
                },
                "secondaryTickers": {
                    "data": []
                },
                "otherTags": {
                    "data": []
                }
            },
            "links": {
                "self": "/article/4292602-mastercard-vast-opportunities-ahead"
            }
        },
        {
            "id": "4291797",
            "type": "article",
            "attributes": {
                "publishOn": "2019-09-16T12:32:45-04:00",
                "isLockedPro": false,
                "commentCount": 9,
                "gettyImageUrl": null,
                "videoPreviewUrl": null,
                "videoDuration": null,
                "themes": {},
                "title": "Mastercard: The 4 Powerful Tailwinds Driving This Business",
                "structuredInsights": null,
                "isPaywalled": false
            },
            "relationships": {
                "author": {
                    "data": {
                        "id": "41961",
                        "type": "author"
                    }
                },
                "sentiments": {
                    "data": [
                        {
                            "id": "67626",
                            "type": "sentiment"
                        }
                    ]
                },
                "primaryTickers": {
                    "data": [
                        {
                            "id": "903",
                            "type": "tag"
                        }
                    ]
                },
                "secondaryTickers": {
                    "data": []
                },
                "otherTags": {
                    "data": []
                }
            },
            "links": {
                "self": "/article/4291797-mastercard-4-powerful-tailwinds-driving-this-business"
            }
        },
        {
            "id": "4291704",
            "type": "article",
            "attributes": {
                "publishOn": "2019-09-16T07:36:07-04:00",
                "isLockedPro": false,
                "commentCount": 12,
                "gettyImageUrl": null,
                "videoPreviewUrl": null,
                "videoDuration": null,
                "themes": {},
                "title": "Mastercard Just Gave Us What We Needed",
                "structuredInsights": null,
                "isPaywalled": false
            },
            "relationships": {
                "author": {
                    "data": {
                        "id": "33291",
                        "type": "author"
                    }
                },
                "sentiments": {
                    "data": [
                        {
                            "id": "67339",
                            "type": "sentiment"
                        }
                    ]
                },
                "primaryTickers": {
                    "data": [
                        {
                            "id": "903",
                            "type": "tag"
                        }
                    ]
                },
                "secondaryTickers": {
                    "data": []
                },
                "otherTags": {
                    "data": []
                }
            },
            "links": {
                "self": "/article/4291704-mastercard-just-gave-us-what-needed"
            }
        },
        {
            "id": "4290190",
            "type": "article",
            "attributes": {
                "publishOn": "2019-09-06T12:43:19-04:00",
                "isLockedPro": false,
                "commentCount": 115,
                "gettyImageUrl": null,
                "videoPreviewUrl": null,
                "videoDuration": null,
                "themes": {},
                "title": "The Pink Portfolio: Mastercard's Growth",
                "structuredInsights": null,
                "isPaywalled": false
            },
            "relationships": {
                "author": {
                    "data": {
                        "id": "100666",
                        "type": "author"
                    }
                },
                "sentiments": {
                    "data": [
                        {
                            "id": "64565",
                            "type": "sentiment"
                        }
                    ]
                },
                "primaryTickers": {
                    "data": [
                        {
                            "id": "903",
                            "type": "tag"
                        }
                    ]
                },
                "secondaryTickers": {
                    "data": []
                },
                "otherTags": {
                    "data": []
                }
            },
            "links": {
                "self": "/article/4290190-pink-portfolio-mastercards-growth"
            }
        },
        {
            "id": "4286232",
            "type": "article",
            "attributes": {
                "publishOn": "2019-08-16T09:46:21-04:00",
                "isLockedPro": false,
                "commentCount": 16,
                "gettyImageUrl": null,
                "videoPreviewUrl": null,
                "videoDuration": null,
                "themes": {},
                "title": "Mastercard: Bolt-On Acquisition Adds To The Impressive Growth Story",
                "structuredInsights": null,
                "isPaywalled": false
            },
            "relationships": {
                "author": {
                    "data": {
                        "id": "105387",
                        "type": "author"
                    }
                },
                "sentiments": {
                    "data": [
                        {
                            "id": "59889",
                            "type": "sentiment"
                        }
                    ]
                },
                "primaryTickers": {
                    "data": [
                        {
                            "id": "903",
                            "type": "tag"
                        }
                    ]
                },
                "secondaryTickers": {
                    "data": []
                },
                "otherTags": {
                    "data": []
                }
            },
            "links": {
                "self": "/article/4286232-mastercard-bolt-on-acquisition-adds-to-impressive-growth-story"
            }
        },
        {
            "id": "4283296",
            "type": "article",
            "attributes": {
                "publishOn": "2019-08-08T13:17:35-04:00",
                "isLockedPro": false,
                "commentCount": 26,
                "gettyImageUrl": null,
                "videoPreviewUrl": null,
                "videoDuration": null,
                "themes": {},
                "title": "Mastercard Is Up 233% Since My Last Article - It Can Double Again",
                "structuredInsights": null,
                "isPaywalled": false
            },
            "relationships": {
                "author": {
                    "data": {
                        "id": "24634",
                        "type": "author"
                    }
                },
                "sentiments": {
                    "data": [
                        {
                            "id": "58608",
                            "type": "sentiment"
                        }
                    ]
                },
                "primaryTickers": {
                    "data": [
                        {
                            "id": "903",
                            "type": "tag"
                        }
                    ]
                },
                "secondaryTickers": {
                    "data": []
                },
                "otherTags": {
                    "data": []
                }
            },
            "links": {
                "self": "/article/4283296-mastercard-is-up-233-percent-since-last-article-can-double-again"
            }
        },
        {
            "id": "4283207",
            "type": "article",
            "attributes": {
                "publishOn": "2019-08-08T12:05:00-04:00",
                "isLockedPro": false,
                "commentCount": 19,
                "gettyImageUrl": null,
                "videoPreviewUrl": null,
                "videoDuration": null,
                "themes": {},
                "title": "Mastercard: The Dip Represents A Potential Buying Opportunity",
                "structuredInsights": null,
                "isPaywalled": false
            },
            "relationships": {
                "author": {
                    "data": {
                        "id": "65113",
                        "type": "author"
                    }
                },
                "sentiments": {
                    "data": [
                        {
                            "id": "58345",
                            "type": "sentiment"
                        }
                    ]
                },
                "primaryTickers": {
                    "data": [
                        {
                            "id": "903",
                            "type": "tag"
                        }
                    ]
                },
                "secondaryTickers": {
                    "data": []
                },
                "otherTags": {
                    "data": []
                }
            },
            "links": {
                "self": "/article/4283207-mastercard-dip-represents-potential-buying-opportunity"
            }
        },
        {
            "id": "4281648",
            "type": "article",
            "attributes": {
                "publishOn": "2019-08-05T10:56:11-04:00",
                "isLockedPro": false,
                "commentCount": 12,
                "gettyImageUrl": null,
                "videoPreviewUrl": null,
                "videoDuration": null,
                "themes": {},
                "title": "Mastercard: Why I'm Not Interested In Taking Profits",
                "structuredInsights": null,
                "isPaywalled": false
            },
            "relationships": {
                "author": {
                    "data": {
                        "id": "41961",
                        "type": "author"
                    }
                },
                "sentiments": {
                    "data": [
                        {
                            "id": "57365",
                            "type": "sentiment"
                        }
                    ]
                },
                "primaryTickers": {
                    "data": [
                        {
                            "id": "903",
                            "type": "tag"
                        }
                    ]
                },
                "secondaryTickers": {
                    "data": []
                },
                "otherTags": {
                    "data": []
                }
            },
            "links": {
                "self": "/article/4281648-mastercard-why-not-interested-in-taking-profits"
            }
        },
        {
            "id": "4280445",
            "type": "article",
            "attributes": {
                "publishOn": "2019-08-01T19:25:27-04:00",
                "isLockedPro": false,
                "commentCount": 24,
                "gettyImageUrl": null,
                "videoPreviewUrl": null,
                "videoDuration": null,
                "themes": {},
                "title": "Fear Of Missing Out (FOMO) And Mastercard",
                "structuredInsights": null,
                "isPaywalled": false
            },
            "relationships": {
                "author": {
                    "data": {
                        "id": "50452",
                        "type": "author"
                    }
                },
                "sentiments": {
                    "data": [
                        {
                            "id": "56688",
                            "type": "sentiment"
                        }
                    ]
                },
                "primaryTickers": {
                    "data": [
                        {
                            "id": "903",
                            "type": "tag"
                        }
                    ]
                },
                "secondaryTickers": {
                    "data": []
                },
                "otherTags": {
                    "data": []
                }
            },
            "links": {
                "self": "/article/4280445-fear-of-missing-out-fomo-and-mastercard"
            }
        },
        {
            "id": "4277792",
            "type": "article",
            "attributes": {
                "publishOn": "2019-07-25T18:48:18-04:00",
                "isLockedPro": false,
                "commentCount": 32,
                "gettyImageUrl": null,
                "videoPreviewUrl": null,
                "videoDuration": null,
                "themes": {},
                "title": "Visa And Mastercard: 2 Stocks, 1 Superior Business Model",
                "structuredInsights": null,
                "isPaywalled": false
            },
            "relationships": {
                "author": {
                    "data": {
                        "id": "102404",
                        "type": "author"
                    }
                },
                "sentiments": {
                    "data": [
                        {
                            "id": "54829",
                            "type": "sentiment"
                        },
                        {
                            "id": "54830",
                            "type": "sentiment"
                        }
                    ]
                },
                "primaryTickers": {
                    "data": [
                        {
                            "id": "903",
                            "type": "tag"
                        }
                    ]
                },
                "secondaryTickers": {
                    "data": []
                },
                "otherTags": {
                    "data": []
                }
            },
            "links": {
                "self": "/article/4277792-visa-and-mastercard-2-stocks-1-superior-business-model"
            }
        },
        {
            "id": "4276090",
            "type": "article",
            "attributes": {
                "publishOn": "2019-07-19T14:08:57-04:00",
                "isLockedPro": false,
                "commentCount": 56,
                "gettyImageUrl": null,
                "videoPreviewUrl": null,
                "videoDuration": null,
                "themes": {},
                "title": "Mastercard Is Ready To Capitalize On Cashless Trend",
                "structuredInsights": null,
                "isPaywalled": false
            },
            "relationships": {
                "author": {
                    "data": {
                        "id": "104502",
                        "type": "author"
                    }
                },
                "sentiments": {
                    "data": [
                        {
                            "id": "53408",
                            "type": "sentiment"
                        }
                    ]
                },
                "primaryTickers": {
                    "data": [
                        {
                            "id": "903",
                            "type": "tag"
                        }
                    ]
                },
                "secondaryTickers": {
                    "data": []
                },
                "otherTags": {
                    "data": []
                }
            },
            "links": {
                "self": "/article/4276090-mastercard-is-ready-to-capitalize-on-cashless-trend"
            }
        },
        {
            "id": "4267916",
            "type": "article",
            "attributes": {
                "publishOn": "2019-06-03T09:30:38-04:00",
                "isLockedPro": false,
                "commentCount": 97,
                "gettyImageUrl": null,
                "videoPreviewUrl": null,
                "videoDuration": null,
                "themes": {},
                "title": "Mastercard And Visa: A Side-By-Side Comparison",
                "structuredInsights": null,
                "isPaywalled": false
            },
            "relationships": {
                "author": {
                    "data": {
                        "id": "105096",
                        "type": "author"
                    }
                },
                "sentiments": {
                    "data": [
                        {
                            "id": "42108",
                            "type": "sentiment"
                        },
                        {
                            "id": "42109",
                            "type": "sentiment"
                        }
                    ]
                },
                "primaryTickers": {
                    "data": [
                        {
                            "id": "903",
                            "type": "tag"
                        }
                    ]
                },
                "secondaryTickers": {
                    "data": []
                },
                "otherTags": {
                    "data": []
                }
            },
            "links": {
                "self": "/article/4267916-mastercard-and-visa-side-side-comparison"
            }
        },
        {
            "id": "4267061",
            "type": "article",
            "attributes": {
                "publishOn": "2019-05-29T13:02:35-04:00",
                "isLockedPro": false,
                "commentCount": 25,
                "gettyImageUrl": null,
                "videoPreviewUrl": null,
                "videoDuration": null,
                "themes": {},
                "title": "There's No Stopping Mastercard's Growth",
                "structuredInsights": null,
                "isPaywalled": false
            },
            "relationships": {
                "author": {
                    "data": {
                        "id": "65113",
                        "type": "author"
                    }
                },
                "sentiments": {
                    "data": [
                        {
                            "id": "41250",
                            "type": "sentiment"
                        }
                    ]
                },
                "primaryTickers": {
                    "data": [
                        {
                            "id": "903",
                            "type": "tag"
                        }
                    ]
                },
                "secondaryTickers": {
                    "data": []
                },
                "otherTags": {
                    "data": []
                }
            },
            "links": {
                "self": "/article/4267061-no-stopping-mastercards-growth"
            }
        },
        {
            "id": "4265049",
            "type": "article",
            "attributes": {
                "publishOn": "2019-05-18T06:09:50-04:00",
                "isLockedPro": false,
                "commentCount": 21,
                "gettyImageUrl": null,
                "videoPreviewUrl": null,
                "videoDuration": null,
                "themes": {},
                "title": "Mastercard: Top Quality And Reasonable Valuation",
                "structuredInsights": null,
                "isPaywalled": false
            },
            "relationships": {
                "author": {
                    "data": {
                        "id": "102764",
                        "type": "author"
                    }
                },
                "sentiments": {
                    "data": [
                        {
                            "id": "38763",
                            "type": "sentiment"
                        }
                    ]
                },
                "primaryTickers": {
                    "data": [
                        {
                            "id": "903",
                            "type": "tag"
                        }
                    ]
                },
                "secondaryTickers": {
                    "data": []
                },
                "otherTags": {
                    "data": []
                }
            },
            "links": {
                "self": "/article/4265049-mastercard-top-quality-and-reasonable-valuation"
            }
        },
        {
            "id": "4264886",
            "type": "article",
            "attributes": {
                "publishOn": "2019-05-17T10:23:44-04:00",
                "isLockedPro": false,
                "commentCount": 46,
                "gettyImageUrl": null,
                "videoPreviewUrl": null,
                "videoDuration": null,
                "themes": {},
                "title": "Visa Vs Mastercard: Who Wins?",
                "structuredInsights": null,
                "isPaywalled": false
            },
            "relationships": {
                "author": {
                    "data": {
                        "id": "102646",
                        "type": "author"
                    }
                },
                "sentiments": {
                    "data": [
                        {
                            "id": "38216",
                            "type": "sentiment"
                        },
                        {
                            "id": "38217",
                            "type": "sentiment"
                        }
                    ]
                },
                "primaryTickers": {
                    "data": [
                        {
                            "id": "903",
                            "type": "tag"
                        }
                    ]
                },
                "secondaryTickers": {
                    "data": []
                },
                "otherTags": {
                    "data": []
                }
            },
            "links": {
                "self": "/article/4264886-visa-vs-mastercard-who-wins"
            }
        },
        {
            "id": "4263326",
            "type": "article",
            "attributes": {
                "publishOn": "2019-05-12T21:49:53-04:00",
                "isLockedPro": false,
                "commentCount": 27,
                "gettyImageUrl": null,
                "videoPreviewUrl": null,
                "videoDuration": null,
                "themes": {},
                "title": "Mastercard: Defensively Buy The Unbroken Outperformer",
                "structuredInsights": null,
                "isPaywalled": false
            },
            "relationships": {
                "author": {
                    "data": {
                        "id": "102548",
                        "type": "author"
                    }
                },
                "sentiments": {
                    "data": [
                        {
                            "id": "37227",
                            "type": "sentiment"
                        }
                    ]
                },
                "primaryTickers": {
                    "data": [
                        {
                            "id": "903",
                            "type": "tag"
                        }
                    ]
                },
                "secondaryTickers": {
                    "data": []
                },
                "otherTags": {
                    "data": []
                }
            },
            "links": {
                "self": "/article/4263326-mastercard-defensively-buy-unbroken-outperformer"
            }
        },
        {
            "id": "4261193",
            "type": "article",
            "attributes": {
                "publishOn": "2019-05-07T18:55:59-04:00",
                "isLockedPro": false,
                "commentCount": 4,
                "gettyImageUrl": null,
                "videoPreviewUrl": null,
                "videoDuration": null,
                "themes": {},
                "title": "Mastercard Agrees To Acquire Transactis For Billing And Payment Tech",
                "structuredInsights": null,
                "isPaywalled": false
            },
            "relationships": {
                "author": {
                    "data": {
                        "id": "101421",
                        "type": "author"
                    }
                },
                "sentiments": {
                    "data": [
                        {
                            "id": "36361",
                            "type": "sentiment"
                        }
                    ]
                },
                "primaryTickers": {
                    "data": [
                        {
                            "id": "903",
                            "type": "tag"
                        }
                    ]
                },
                "secondaryTickers": {
                    "data": []
                },
                "otherTags": {
                    "data": []
                }
            },
            "links": {
                "self": "/article/4261193-mastercard-agrees-to-acquire-transactis-for-billing-and-payment-tech"
            }
        },
        {
            "id": "4258269",
            "type": "article",
            "attributes": {
                "publishOn": "2019-04-30T19:40:49-04:00",
                "isLockedPro": false,
                "commentCount": 15,
                "gettyImageUrl": null,
                "videoPreviewUrl": null,
                "videoDuration": null,
                "themes": {},
                "title": "Mastercard: A Squeaky Clean Quarter",
                "structuredInsights": null,
                "isPaywalled": false
            },
            "relationships": {
                "author": {
                    "data": {
                        "id": "92586",
                        "type": "author"
                    }
                },
                "sentiments": {
                    "data": [
                        {
                            "id": "34710",
                            "type": "sentiment"
                        }
                    ]
                },
                "primaryTickers": {
                    "data": [
                        {
                            "id": "903",
                            "type": "tag"
                        }
                    ]
                },
                "secondaryTickers": {
                    "data": []
                },
                "otherTags": {
                    "data": []
                }
            },
            "links": {
                "self": "/article/4258269-mastercard-squeaky-clean-quarter"
            }
        },
        {
            "id": "4255404",
            "type": "article",
            "attributes": {
                "publishOn": "2019-04-18T23:13:31-04:00",
                "isLockedPro": false,
                "commentCount": 14,
                "gettyImageUrl": null,
                "videoPreviewUrl": null,
                "videoDuration": null,
                "themes": {},
                "title": "Mastercard Acquires Vyze For Point-Of-Sale Tech",
                "structuredInsights": null,
                "isPaywalled": false
            },
            "relationships": {
                "author": {
                    "data": {
                        "id": "101421",
                        "type": "author"
                    }
                },
                "sentiments": {
                    "data": [
                        {
                            "id": "32109",
                            "type": "sentiment"
                        }
                    ]
                },
                "primaryTickers": {
                    "data": [
                        {
                            "id": "903",
                            "type": "tag"
                        }
                    ]
                },
                "secondaryTickers": {
                    "data": []
                },
                "otherTags": {
                    "data": []
                }
            },
            "links": {
                "self": "/article/4255404-mastercard-acquires-vyze-for-point-of-sale-tech"
            }
        },
        {
            "id": "4252082",
            "type": "article",
            "attributes": {
                "publishOn": "2019-04-01T09:53:56-04:00",
                "isLockedPro": false,
                "commentCount": 64,
                "gettyImageUrl": null,
                "videoPreviewUrl": null,
                "videoDuration": null,
                "themes": {},
                "title": "Mastercard: When Growth Beats Value",
                "structuredInsights": null,
                "isPaywalled": false
            },
            "relationships": {
                "author": {
                    "data": {
                        "id": "105096",
                        "type": "author"
                    }
                },
                "sentiments": {
                    "data": [
                        {
                            "id": "27339",
                            "type": "sentiment"
                        }
                    ]
                },
                "primaryTickers": {
                    "data": [
                        {
                            "id": "903",
                            "type": "tag"
                        }
                    ]
                },
                "secondaryTickers": {
                    "data": []
                },
                "otherTags": {
                    "data": [
                        {
                            "id": "1302",
                            "type": "tag"
                        }
                    ]
                }
            },
            "links": {
                "self": "/article/4252082-mastercard-when-growth-beats-value"
            }
        },
        {
            "id": "4243851",
            "type": "article",
            "attributes": {
                "publishOn": "2019-02-25T10:17:30-05:00",
                "isLockedPro": false,
                "commentCount": 26,
                "gettyImageUrl": null,
                "videoPreviewUrl": null,
                "videoDuration": null,
                "themes": {},
                "title": "Mastercard: A Company I Want To Own More Of In 2019",
                "structuredInsights": null,
                "isPaywalled": false
            },
            "relationships": {
                "author": {
                    "data": {
                        "id": "98446",
                        "type": "author"
                    }
                },
                "sentiments": {
                    "data": [
                        {
                            "id": "9168",
                            "type": "sentiment"
                        }
                    ]
                },
                "primaryTickers": {
                    "data": [
                        {
                            "id": "903",
                            "type": "tag"
                        }
                    ]
                },
                "secondaryTickers": {
                    "data": []
                },
                "otherTags": {
                    "data": []
                }
            },
            "links": {
                "self": "/article/4243851-mastercard-company-i-want-to-own-of-in-2019"
            }
        },
        {
            "id": "4242408",
            "type": "article",
            "attributes": {
                "publishOn": "2019-02-20T08:55:02-05:00",
                "isLockedPro": false,
                "commentCount": 16,
                "gettyImageUrl": null,
                "videoPreviewUrl": null,
                "videoDuration": null,
                "themes": {},
                "title": "Should Mastercard Be Bought Here?",
                "structuredInsights": null,
                "isPaywalled": false
            },
            "relationships": {
                "author": {
                    "data": {
                        "id": "104579",
                        "type": "author"
                    }
                },
                "sentiments": {
                    "data": [
                        {
                            "id": "8699",
                            "type": "sentiment"
                        }
                    ]
                },
                "primaryTickers": {
                    "data": [
                        {
                            "id": "903",
                            "type": "tag"
                        }
                    ]
                },
                "secondaryTickers": {
                    "data": []
                },
                "otherTags": {
                    "data": []
                }
            },
            "links": {
                "self": "/article/4242408-should-mastercard-be-bought"
            }
        },
        {
            "id": "4240357",
            "type": "article",
            "attributes": {
                "publishOn": "2019-02-12T18:23:29-05:00",
                "isLockedPro": false,
                "commentCount": 25,
                "gettyImageUrl": null,
                "videoPreviewUrl": null,
                "videoDuration": null,
                "themes": {},
                "title": "Mastercard: Crushing The Market",
                "structuredInsights": null,
                "isPaywalled": false
            },
            "relationships": {
                "author": {
                    "data": {
                        "id": "104122",
                        "type": "author"
                    }
                },
                "sentiments": {
                    "data": [
                        {
                            "id": "7806",
                            "type": "sentiment"
                        }
                    ]
                },
                "primaryTickers": {
                    "data": [
                        {
                            "id": "903",
                            "type": "tag"
                        }
                    ]
                },
                "secondaryTickers": {
                    "data": []
                },
                "otherTags": {
                    "data": []
                }
            },
            "links": {
                "self": "/article/4240357-mastercard-crushing-market"
            }
        },
        {
            "id": "4238957",
            "type": "article",
            "attributes": {
                "publishOn": "2019-02-07T09:10:40-05:00",
                "isLockedPro": false,
                "commentCount": 9,
                "gettyImageUrl": null,
                "videoPreviewUrl": null,
                "videoDuration": null,
                "themes": {},
                "title": "Is Mastercard Poised To Slow Down?",
                "structuredInsights": null,
                "isPaywalled": false
            },
            "relationships": {
                "author": {
                    "data": {
                        "id": "50452",
                        "type": "author"
                    }
                },
                "sentiments": {
                    "data": [
                        {
                            "id": "7388",
                            "type": "sentiment"
                        }
                    ]
                },
                "primaryTickers": {
                    "data": [
                        {
                            "id": "903",
                            "type": "tag"
                        }
                    ]
                },
                "secondaryTickers": {
                    "data": []
                },
                "otherTags": {
                    "data": []
                }
            },
            "links": {
                "self": "/article/4238957-is-mastercard-poised-to-slow-down"
            }
        },
        {
            "id": "4230926",
            "type": "article",
            "attributes": {
                "publishOn": "2018-12-31T20:41:50-05:00",
                "isLockedPro": false,
                "commentCount": 45,
                "gettyImageUrl": null,
                "videoPreviewUrl": null,
                "videoDuration": null,
                "themes": {},
                "title": "Mastercard: Great Company But Still Expensive",
                "structuredInsights": null,
                "isPaywalled": false
            },
            "relationships": {
                "author": {
                    "data": {
                        "id": "104254",
                        "type": "author"
                    }
                },
                "sentiments": {
                    "data": []
                },
                "primaryTickers": {
                    "data": [
                        {
                            "id": "903",
                            "type": "tag"
                        }
                    ]
                },
                "secondaryTickers": {
                    "data": []
                },
                "otherTags": {
                    "data": []
                }
            },
            "links": {
                "self": "/article/4230926-mastercard-great-company-still-expensive"
            }
        }
    ]
}