{
    "data": [
        {
            "id": "4230763",
            "type": "article",
            "attributes": {
                "publishOn": "2018-12-31T05:10:09-05:00",
                "isLockedPro": false,
                "commentCount": 2,
                "gettyImageUrl": null,
                "videoPreviewUrl": null,
                "videoDuration": null,
                "themes": {},
                "title": "LHC Group: A Solid Bet, Obamacare Or Not",
                "structuredInsights": null,
                "isPaywalled": false
            },
            "relationships": {
                "author": {
                    "data": {
                        "id": "104761",
                        "type": "author"
                    }
                },
                "sentiments": {
                    "data": [
                        {
                            "id": "3150",
                            "type": "sentiment"
                        }
                    ]
                },
                "primaryTickers": {
                    "data": [
                        {
                            "id": "1719",
                            "type": "tag"
                        }
                    ]
                },
                "secondaryTickers": {
                    "data": []
                },
                "otherTags": {
                    "data": []
                }
            },
            "links": {
                "self": "/article/4230763-lhc-group-solid-bet-obamacare-not"
            }
        },
        {
            "id": "4226638",
            "type": "article",
            "attributes": {
                "publishOn": "2018-12-06T05:29:59-05:00",
                "isLockedPro": false,
                "commentCount": 1,
                "gettyImageUrl": null,
                "videoPreviewUrl": null,
                "videoDuration": null,
                "themes": {},
                "title": "LHC Group: A Leader With Plenty Of Growth Runway In $100 Billion Market",
                "structuredInsights": null,
                "isPaywalled": false
            },
            "relationships": {
                "author": {
                    "data": {
                        "id": "104761",
                        "type": "author"
                    }
                },
                "sentiments": {
                    "data": [
                        {
                            "id": "144",
                            "type": "sentiment"
                        }
                    ]
                },
                "primaryTickers": {
                    "data": [
                        {
                            "id": "1719",
                            "type": "tag"
                        }
                    ]
                },
                "secondaryTickers": {
                    "data": []
                },
                "otherTags": {
                    "data": []
                }
            },
            "links": {
                "self": "/article/4226638-lhc-group-leader-plenty-of-growth-runway-in-100-billion-market"
            }
        },
        {
            "id": "4222217",
            "type": "article",
            "attributes": {
                "publishOn": "2018-11-14T14:53:23-05:00",
                "isLockedPro": false,
                "commentCount": 18,
                "gettyImageUrl": null,
                "videoPreviewUrl": null,
                "videoDuration": null,
                "themes": {},
                "title": "Buy UnitedHealth Group After The Dip",
                "structuredInsights": null,
                "isPaywalled": false
            },
            "relationships": {
                "author": {
                    "data": {
                        "id": "22786",
                        "type": "author"
                    }
                },
                "sentiments": {
                    "data": [
                        {
                            "id": "21778",
                            "type": "sentiment"
                        }
                    ]
                },
                "primaryTickers": {
                    "data": [
                        {
                            "id": "1719",
                            "type": "tag"
                        }
                    ]
                },
                "secondaryTickers": {
                    "data": []
                },
                "otherTags": {
                    "data": []
                }
            },
            "links": {
                "self": "/article/4222217-buy-unitedhealth-group-after-dip"
            }
        },
        {
            "id": "4205513",
            "type": "article",
            "attributes": {
                "publishOn": "2018-09-11T09:17:42-04:00",
                "isLockedPro": false,
                "commentCount": 11,
                "gettyImageUrl": null,
                "videoPreviewUrl": null,
                "videoDuration": null,
                "themes": {},
                "title": "UnitedHealth Group: I Disagree With The Recent Downgrade",
                "structuredInsights": null,
                "isPaywalled": false
            },
            "relationships": {
                "author": {
                    "data": {
                        "id": "86896",
                        "type": "author"
                    }
                },
                "sentiments": {
                    "data": []
                },
                "primaryTickers": {
                    "data": [
                        {
                            "id": "1719",
                            "type": "tag"
                        }
                    ]
                },
                "secondaryTickers": {
                    "data": []
                },
                "otherTags": {
                    "data": []
                }
            },
            "links": {
                "self": "/article/4205513-unitedhealth-group-i-disagree-recent-downgrade"
            }
        },
        {
            "id": "4205031",
            "type": "article",
            "attributes": {
                "publishOn": "2018-09-07T17:32:40-04:00",
                "isLockedPro": false,
                "commentCount": 38,
                "gettyImageUrl": null,
                "videoPreviewUrl": null,
                "videoDuration": null,
                "themes": {},
                "title": "UnitedHealth's Share Price Will Continue Its Rapid Uptrend",
                "structuredInsights": null,
                "isPaywalled": false
            },
            "relationships": {
                "author": {
                    "data": {
                        "id": "104718",
                        "type": "author"
                    }
                },
                "sentiments": {
                    "data": [
                        {
                            "id": "19505",
                            "type": "sentiment"
                        }
                    ]
                },
                "primaryTickers": {
                    "data": [
                        {
                            "id": "1719",
                            "type": "tag"
                        }
                    ]
                },
                "secondaryTickers": {
                    "data": []
                },
                "otherTags": {
                    "data": []
                }
            },
            "links": {
                "self": "/article/4205031-unitedhealths-share-price-will-continue-rapid-uptrend"
            }
        },
        {
            "id": "4203123",
            "type": "article",
            "attributes": {
                "publishOn": "2018-08-30T11:37:39-04:00",
                "isLockedPro": false,
                "commentCount": 10,
                "gettyImageUrl": null,
                "videoPreviewUrl": null,
                "videoDuration": null,
                "themes": {},
                "title": "UnitedHealth Group Is A Solid Buy For 2018",
                "structuredInsights": null,
                "isPaywalled": false
            },
            "relationships": {
                "author": {
                    "data": {
                        "id": "102293",
                        "type": "author"
                    }
                },
                "sentiments": {
                    "data": [
                        {
                            "id": "19222",
                            "type": "sentiment"
                        }
                    ]
                },
                "primaryTickers": {
                    "data": [
                        {
                            "id": "1719",
                            "type": "tag"
                        }
                    ]
                },
                "secondaryTickers": {
                    "data": []
                },
                "otherTags": {
                    "data": []
                }
            },
            "links": {
                "self": "/article/4203123-unitedhealth-group-is-solid-buy-for-2018"
            }
        },
        {
            "id": "4192311",
            "type": "article",
            "attributes": {
                "publishOn": "2018-07-31T06:06:06-04:00",
                "isLockedPro": false,
                "commentCount": 0,
                "gettyImageUrl": null,
                "videoPreviewUrl": null,
                "videoDuration": null,
                "themes": {},
                "title": "U.S. Equity Strategy Q2 2018 Commentary",
                "structuredInsights": null,
                "isPaywalled": false
            },
            "relationships": {
                "author": {
                    "data": {
                        "id": "104655",
                        "type": "author"
                    }
                },
                "sentiments": {
                    "data": []
                },
                "primaryTickers": {
                    "data": [
                        {
                            "id": "1719",
                            "type": "tag"
                        }
                    ]
                },
                "secondaryTickers": {
                    "data": []
                },
                "otherTags": {
                    "data": [
                        {
                            "id": "576527",
                            "type": "tag"
                        }
                    ]
                }
            },
            "links": {
                "self": "/article/4192311-u-s-equity-strategy-q2-2018-commentary"
            }
        },
        {
            "id": "4189424",
            "type": "article",
            "attributes": {
                "publishOn": "2018-07-24T09:23:55-04:00",
                "isLockedPro": false,
                "commentCount": 25,
                "gettyImageUrl": null,
                "videoPreviewUrl": null,
                "videoDuration": null,
                "themes": {},
                "title": "UnitedHealth Group: Buy Or Sell?",
                "structuredInsights": null,
                "isPaywalled": false
            },
            "relationships": {
                "author": {
                    "data": {
                        "id": "101863",
                        "type": "author"
                    }
                },
                "sentiments": {
                    "data": [
                        {
                            "id": "17750",
                            "type": "sentiment"
                        }
                    ]
                },
                "primaryTickers": {
                    "data": [
                        {
                            "id": "1719",
                            "type": "tag"
                        }
                    ]
                },
                "secondaryTickers": {
                    "data": []
                },
                "otherTags": {
                    "data": []
                }
            },
            "links": {
                "self": "/article/4189424-unitedhealth-group-buy-sell"
            }
        },
        {
            "id": "4189065",
            "type": "article",
            "attributes": {
                "publishOn": "2018-07-23T03:20:01-04:00",
                "isLockedPro": false,
                "commentCount": 3,
                "gettyImageUrl": null,
                "videoPreviewUrl": null,
                "videoDuration": null,
                "themes": {},
                "title": "UnitedHealth Group: Using Data To Modernize The Patient Experience",
                "structuredInsights": null,
                "isPaywalled": false
            },
            "relationships": {
                "author": {
                    "data": {
                        "id": "99196",
                        "type": "author"
                    }
                },
                "sentiments": {
                    "data": [
                        {
                            "id": "17688",
                            "type": "sentiment"
                        }
                    ]
                },
                "primaryTickers": {
                    "data": [
                        {
                            "id": "1719",
                            "type": "tag"
                        }
                    ]
                },
                "secondaryTickers": {
                    "data": []
                },
                "otherTags": {
                    "data": []
                }
            },
            "links": {
                "self": "/article/4189065-unitedhealth-group-using-data-to-modernize-patient-experience"
            }
        },
        {
            "id": "4180729",
            "type": "article",
            "attributes": {
                "publishOn": "2018-06-11T10:03:11-04:00",
                "isLockedPro": false,
                "commentCount": 12,
                "gettyImageUrl": null,
                "videoPreviewUrl": null,
                "videoDuration": null,
                "themes": {},
                "title": "UnitedHealth Group: Buy For Great Total Return And 20% Dividend Growth",
                "structuredInsights": null,
                "isPaywalled": false
            },
            "relationships": {
                "author": {
                    "data": {
                        "id": "85096",
                        "type": "author"
                    }
                },
                "sentiments": {
                    "data": [
                        {
                            "id": "238669",
                            "type": "sentiment"
                        }
                    ]
                },
                "primaryTickers": {
                    "data": [
                        {
                            "id": "1719",
                            "type": "tag"
                        }
                    ]
                },
                "secondaryTickers": {
                    "data": []
                },
                "otherTags": {
                    "data": []
                }
            },
            "links": {
                "self": "/article/4180729-unitedhealth-group-buy-for-great-total-return-and-20-percent-dividend-growth"
            }
        },
        {
            "id": "4166253",
            "type": "article",
            "attributes": {
                "publishOn": "2018-04-26T13:04:25-04:00",
                "isLockedPro": false,
                "commentCount": 2,
                "gettyImageUrl": null,
                "videoPreviewUrl": null,
                "videoDuration": null,
                "themes": {},
                "title": "UnitedHealth Pioneering The Move To An Integrated Accountable Healthcare System",
                "structuredInsights": null,
                "isPaywalled": false
            },
            "relationships": {
                "author": {
                    "data": {
                        "id": "102306",
                        "type": "author"
                    }
                },
                "sentiments": {
                    "data": []
                },
                "primaryTickers": {
                    "data": [
                        {
                            "id": "1719",
                            "type": "tag"
                        }
                    ]
                },
                "secondaryTickers": {
                    "data": []
                },
                "otherTags": {
                    "data": []
                }
            },
            "links": {
                "self": "/article/4166253-unitedhealth-pioneering-move-to-integrated-accountable-healthcare-system"
            }
        },
        {
            "id": "4142151",
            "type": "article",
            "attributes": {
                "publishOn": "2018-02-01T11:12:07-05:00",
                "isLockedPro": false,
                "commentCount": 5,
                "gettyImageUrl": null,
                "videoPreviewUrl": null,
                "videoDuration": null,
                "themes": {},
                "title": "RiverPark Large Growth Fund Q4 2017 Performance Summary",
                "structuredInsights": null,
                "isPaywalled": false
            },
            "relationships": {
                "author": {
                    "data": {
                        "id": "103612",
                        "type": "author"
                    }
                },
                "sentiments": {
                    "data": []
                },
                "primaryTickers": {
                    "data": [
                        {
                            "id": "1719",
                            "type": "tag"
                        }
                    ]
                },
                "secondaryTickers": {
                    "data": []
                },
                "otherTags": {
                    "data": [
                        {
                            "id": "576527",
                            "type": "tag"
                        }
                    ]
                }
            },
            "links": {
                "self": "/article/4142151-riverpark-large-growth-fund-q4-2017-performance-summary"
            }
        },
        {
            "id": "4141689",
            "type": "article",
            "attributes": {
                "publishOn": "2018-01-31T12:19:57-05:00",
                "isLockedPro": false,
                "commentCount": 35,
                "gettyImageUrl": null,
                "videoPreviewUrl": null,
                "videoDuration": null,
                "themes": {},
                "title": "Amazon Insurance For UnitedHealth",
                "structuredInsights": null,
                "isPaywalled": false
            },
            "relationships": {
                "author": {
                    "data": {
                        "id": "23998",
                        "type": "author"
                    }
                },
                "sentiments": {
                    "data": []
                },
                "primaryTickers": {
                    "data": [
                        {
                            "id": "1719",
                            "type": "tag"
                        }
                    ]
                },
                "secondaryTickers": {
                    "data": []
                },
                "otherTags": {
                    "data": []
                }
            },
            "links": {
                "self": "/article/4141689-amazon-insurance-for-unitedhealth"
            }
        }
    ]
}